Workbook

Sheet 🏆 Dashboard
A1: 🎯 BPSC TRE 4.0 — MY PROGRESS DASHBOARD
A2: PROGRESS SUMMARY
A3: 📅 Total Days in Plan | B3: 170 | C3: days
A4: ✅ Days Completed | B4: =COUNTIF('📅 Daily Tracker'!H3:H172,"✅") | C4: days
A5: 🔄 Days In Progress | B5: =COUNTIF('📅 Daily Tracker'!H3:H172,"🔄") | C5: days
A6: ⬜ Days Remaining | B6: =170-B4-B5 | C6: days
A7: 📊 Overall Completion | B7: =(B4/170)*100 | C7: %
A8: 📝 CS Topics Covered | B8: =COUNTIF('✅ CS Checklist'!D3:D61,">0") | C8: / 59 topics
A9: 📖 GS Topics Covered | B9: =COUNTIF('📖 GS Tracker'!C3:C26,"✅") | C9: / 24 topics
A10: 🧪 Mock Tests Done | B10: =COUNTA('📝 Mock Test Log'!G3:G14)-COUNTBLANK('📝 Mock Test Log'!G3:G14) | C10: / 12 tests
A12: TARGET SCORES
A13: Section | B13: Max Marks | C13: My Target | D13: Topper Target
A14: Language | B14: 30 | C14: 25 | D14: 28
A15: General Studies | B15: 40 | C15: 36 | D15: 38
A16: Computer Science | B16: 80 | C16: 68 | D16: 72
A17: TOTAL | B17: 150 | C17: 129 | D17: 138
A19: 💪 YOU CLEARED BIHAR STET. YOUR FUNDAMENTALS ARE SOLID. NOW EXECUTE THE PLAN! 🎯
A20: ⚠️ KEY REMINDERS
A21: Option D ('More than one'): | B21: ~20–25% of answers are D — NEVER ignore it!
A22: Option E ('None of the above'): | B22: Some correct answers ARE 'none' — check carefully
A23: GS is 40 marks: | B23: Toppers score 36–38. Easy marks — don't neglect!
A24: Language is qualifying: | B24: Need min 9/30 — aim for 25+. Failing = disqualified
A25: Time per question: | B25: Max 90 seconds. Move on; return to difficult ones
A26: Solve ALL 3 PYQs 3x each: | B26: Exam setter repeats topics. 3 rounds = mastery
A27: Today's mentor: | B27: Come daily with 'Day-N' → Claude teaches you that topic!

Sheet 📅 Daily Tracker
A1: 🎯 BPSC TRE 4.0 — DAILY STUDY TRACKER | Computer Science Teacher (Class 11–12) | Target: 130+/150
A2: Day | B2: Date (Fill In) | C2: Phase | D2: Week | E2: CS Topic | F2: GS Topic | G2: Key PYQ Fact / Note | H2: Status (✅/🔄/⬜) | I2: CS Score (/10) | J2: GS Score (/10) | K2: PYQ Qs Solved | L2: Mock Test # | M2: Completion % | N2: Weak Areas (Write here) | O2: Revision Needed (Y/N) | P2: Time Spent (hours) | Q2: Confidence (1-10) | R2: Personal Notes
A3: 1 | C3: 🟥 Phase 1: Foundation | D3: Week 1 | E3: OOP Fundamentals — 4 Pillars, Class vs Object | F3: Maths — Percentage Basics | G3: 4 pillars: Encapsulation, Inheritance, Polymorphism, Abstraction | M3: =IF(H3="✅",100,IF(H3="🔄",50,0))
A4: 2 | C4: 🟥 Phase 1: Foundation | D4: Week 1 | E4: Encapsulation & Abstraction | F4: Maths — Profit & Loss | G4: Abstract class = at least 1 pure virtual function | M4: =IF(H4="✅",100,IF(H4="🔄",50,0))
A5: 3 | C5: 🟥 Phase 1: Foundation | D5: Week 1 | E5: Inheritance Types: Single/Multiple/Multilevel/Hierarchical/Hybrid | F5: Maths — Ratio & Proportion | G5: C++ syntax: class Derived : access Base {} | M5: =IF(H5="✅",100,IF(H5="🔄",50,0))
A6: 4 | C6: 🟥 Phase 1: Foundation | D6: Week 1 | E6: Virtual Inheritance & Diamond Problem | F6: Maths — Number System Basics | G6: Virtual inheritance avoids diamond problem | M6: =IF(H6="✅",100,IF(H6="🔄",50,0))
A7: 5 | C7: 🟥 Phase 1: Foundation | D7: Week 1 | E7: Polymorphism: Compile-time & Runtime | F7: Maths — Averages | G7: Runtime polymorphism = virtual functions (overriding) | M7: =IF(H7="✅",100,IF(H7="🔄",50,0))
A8: 6 | C8: 🟥 Phase 1: Foundation | D8: Week 1 | E8: Constructors & Destructors | F8: Maths — LCM & HCF | G8: Only ONE destructor per class; called when object out of scope | M8: =IF(H8="✅",100,IF(H8="🔄",50,0))
A9: 7 | C9: 🟥 Phase 1: Foundation | D9: Week 1 | E9: REVISION: OOP Week 1 + 20 PYQ MCQs | F9: Quick Maths Revision | G9: REVISION DAY | M9: =IF(H9="✅",100,IF(H9="🔄",50,0))
A10: 8 | C10: 🟥 Phase 1: Foundation | D10: Week 2 | E10: C++ Variables, Data Types, Naming Rules | F10: Modern Indian History — Overview | G10: sizeof() does NOT evaluate; 123Variable is INVALID | M10: =IF(H10="✅",100,IF(H10="🔄",50,0))
A11: 9 | C11: 🟥 Phase 1: Foundation | D11: Week 2 | E11: Pointers in C++: NULL, delete, new vs malloc | F11: Champaran Satyagraha 1917 | G11: delete NULL pointer = safe (no crash) | M11: =IF(H11="✅",100,IF(H11="🔄",50,0))
A12: 10 | C12: 🟥 Phase 1: Foundation | D12: Week 2 | E12: Arrays in C++: 1D/2D, is_array(), rank() | F12: Non-Cooperation Movement | G12: char s1[]+s2[] = COMPILE ERROR (can't use + with char arrays) | M12: =IF(H12="✅",100,IF(H12="🔄",50,0))
A13: 11 | C13: 🟥 Phase 1: Foundation | D13: Week 2 | E13: File Handling: ios::in/out/trunc/app/binary | F13: Civil Disobedience & Salt March | G13: ios::trunc truncates file to zero; Ctrl+F9 = compile+run in TC++ | M13: =IF(H13="✅",100,IF(H13="🔄",50,0))
A14: 12 | C14: 🟥 Phase 1: Foundation | D14: Week 2 | E14: Exception Handling (try/catch/throw) & Inline Functions | F14: Quit India Movement 1942 | G14: Inline functions = SMALL & SIMPLE (not large/complex) | M14: =IF(H14="✅",100,IF(H14="🔄",50,0))
... A172: 170 | C172: 🟦 Phase 4: Final Sprint | D172: Week 24 | E172: 🎯 EXAM DAY — BPSC TRE 4.0 | F172: — | G172: 🏆 GIVE YOUR BEST! | M172: =IF(H172="✅",100,IF(H172="🔄",50,0))

Sheet 📊 Phase Overview
A1: BPSC TRE 4.0 — PHASE & TOPIC OVERVIEW
A3: Phase | B3: Days | C3: Month | D3: Topics Covered | E3: Milestone Goal | F3: Duration | G3: Daily Time
A4: 🟥 Phase 1: Foundation | B4: Day 1–60 | C4: April–May 2026 | D4: OOP, C++, Data Structures, DBMS, Computer Networks | E4: Solve TRE 1.0 PYQ once; Write topic notes | F4: 60 days | G4: 4 hrs/day
A5: 🟨 Phase 2: Depth Building | B5: Day 61–120 | C5: June–July 2026 | D5: Digital Electronics, Operating Systems, Computer Architecture, Algorithms, AI/IoT, Web Tech | E5: Solve TRE 2.0 & 3.0 PYQ; 3 Full Mock Tests | F5: 60 days | G5: 5–6 hrs/day
A6: 🟩 Phase 3: Practice | B6: Day 121–150 | C6: August 2026 | D6: Mock Tests, Weak Area Fixing, All 3 PYQ Papers Round 3, Speed Training | E6: 12 Mock Tests total; PYQ Papers solved 3 times each; 130+ target | F6: 30 days | G6: 6 hrs/day
A7: 🟦 Phase 4: Final Sprint | B7: Day 151–170 | C7: September 2026 | D7: PYQ Revision, Formula Sheets, Language Section, Exam Simulation | E7: Light revision only; Formula sheet; Exam Day Strategy | F7: 20 days | G7: 3 hrs/day
A10: 📊 CS TOPIC WEIGHT ANALYSIS (Based on TRE 1.0 + 2.0 + 3.0)
A11: Topic | B11: TRE 1.0 | C11: TRE 2.0 | D11: TRE 3.0 | E11: TOTAL | F11: % of CS | G11: Expected in TRE 4.0 | H11: Priority
A12: OOP / C++ Programming | B12: 22 | C12: 25 | D12: 4 | E12: =C12+D12+E12 | F12: =F12/240*100 | G12: ~16 Questions | H12: 🔴 TIER 1 — MUST MASTER
A13: Data Structures & Algorithms | B13: 14 | C13: 14 | D13: 16 | E13: =C13+D13+E13 | F13: =F13/240*100 | G13: ~14 Questions | H13: 🔴 TIER 1 — MUST MASTER
A14: DBMS & SQL | B14: 12 | C14: 12 | D14: 5 | E14: =C14+D14+E14 | F14: =F14/240*100 | G14: ~10 Questions | H14: 🔴 TIER 1 — MUST MASTER
A15: Computer Networks | B15: 10 | C15: 10 | D15: 6 | E15: =C15+D15+E15 | F15: =F15/240*100 | G15: ~8 Questions | H15: 🔴 TIER 1 — MUST MASTER
A16: Digital Electronics & Logic | B16: 5 | C16: 3 | D16: 16 | E16: =C16+D16+E16 | F16: =F16/240*100 | G16: ~12 Questions | H16: 🟡 TIER 2 — IMPORTANT
A17: Operating Systems | B17: 2 | C17: 2 | D17: 13 | E17: =C17+D17+E17 | F17: =F17/240*100 | G17: ~10 Questions | H17: 🟡 TIER 2 — IMPORTANT
A18: Programming Basics (General) | B18: 5 | C18: 12 | D18: 9 | E18: =C18+D18+E18 | F18: =F18/240*100 | G18: ~8 Questions | H18: 🟡 TIER 2 — IMPORTANT
A19: Computer Architecture | B19: 6 | C19: 2 | D19: 0 | E19: =C19+D19+E19 | F19: =F19/240*100 | G19: ~5 Questions | H19: 🟡 TIER 2 — IMPORTANT
A20: Software Engineering | B20: 0 | C20: 0 | D20: 5 | E20: =C20+D20+E20 | F20: =F20/240*100 | G20: ~4 Questions | H20: 🟢 TIER 3 — GOOD TO KNOW
A21: AI / ML / IoT | B21: 0 | C21: 0 | D21: 4 | E21: =C21+D21+E21 | F21: =F21/240*100 | G21: ~4 Questions | H21: 🟢 TIER 3 — GOOD TO KNOW
A22: Web Technologies / TOC | B22: 2 | C22: 0 | D22: 2 | E22: =C22+D22+E22 | F22: =F22/240*100 | G22: ~4 Questions | H22: 🟢 TIER 3 — GOOD TO KNOW

Sheet 📖 GS Tracker
A1: GENERAL STUDIES TRACKER — Target: 36–38 / 40 Marks
A2: GS Subject | B2: Topic | C2: Status (✅/🔄/⬜) | D2: Days Covered | E2: Key Facts to Remember | F2: PYQs Solved | G2: Self Score (/10) | H2: Notes
A3: Mathematics | B3: Percentage, Profit & Loss, Ratio & Proportion | D3: Day 1–6 | E3: Profit%=(Profit/CP)×100; Cross multiplication for ratio
A4: Mathematics | B4: Number System, LCM, HCF, Averages | D4: Day 6–7 | E4: LCM×HCF=Product of two numbers; Mean is affected by transformations
A5: Mathematics | B5: Work & Time, Speed-Distance-Time | D5: Day 52 | E5: Work=1/Days; D=S×T; Combined work=sum of individual rates
A6: Mathematics | B6: Quadratic Equations, Mensuration, Statistics | D6: Day 52 | E6: TSA of cylinder=2πr(r+h); Sum of roots=-b/a; Product=c/a
A7: History | B7: Champaran 1917, Bihar Provincial Congress 1908 | D7: Day 9,53 | E7: Gandhi+Rajendra Prasad; BPC founded 1908 HQ Patna
A8: History | B8: Ghadar Party, Abhinav Bharat, Birsa Munda | D8: Day 36,53 | E8: Ghadar=USA; Abhinav Bharat=Savarkar London; Birsa's C-in-C=Gaya Munda
A9: History | B9: INC Sessions, Jallianwala Bagh 1919, 1857 Revolt | D9: Day 53 | E9: INC Gaya 1922=Chittaranjan Das; JB Viceroy=Chelmsford; 1857=Savarkar
A10: History | B10: Bihar Socialist Party, AIKS Bihar 1936, Home Rule | D10: Day 53 | E10: BSP=Phulan Prasad+JP Narayan; AIKS=Swami Sahajanand Saraswati
A11: History | B11: Bardoli Satyagraha, Quit India, INC Presidents | D11: Day 53 | E11: Bardoli=Sardar Patel; First INC President=W.C. Bonnerjee
A12: Geography | B12: Bihar: 8.58% population, Rohtas=paddy, Bhagalpur=silk | D12: Day 55,110 | E12: Bihar pop=8.58% of India; Rohtas=max paddy production
A13: Geography | B13: Eastern Ghats, Malnad, Black Soil, East-West Corridor | D13: Day 55 | E13: Highest Eastern Ghats=Mahendragiri; Malnad=Karnataka Plateau
A14: Geography | B14: Climate: Monsoon withdrawal, Stalactites/Stalagmites | D14: Day 55 | E14: SW monsoon withdrawal Hyderabad=1st Oct; Stalactites=hanging
... A26: Bihar GK | B26: First Bhojpuri Film, Silent Valley, Max Urbanization | D26: Day 110 | E26: First Bhojpuri film=Ganga Maiya Tohe Piyari Chadhaibo; Goa=max urban

Sheet ✅ CS Checklist
A1: CS TOPIC MASTERY CHECKLIST — Track Your Level (1=Concept, 2=PYQ, 3=Notes, 4=Recall)
A2: Unit | B2: Sub-Topic | C2: Study Day | D2: Level (1-4) | E2: PYQ Count (All Papers) | F2: Notes
A3: OOP & C++ | B3: 4 Pillars: Encapsulation, Inheritance, Polymorphism, Abstraction | C3: 1-2 | E3: 15+
A4: OOP & C++ | B4: Class vs Object, Instance vs Class Variables | C4: 1 | E4: 5+
A5: OOP & C++ | B5: Inheritance: 5 Types, C++ syntax, Java extends | C5: 3 | E5: 10+
A6: OOP & C++ | B6: Abstract Class = pure virtual function; Virtual vs Pure Virtual | C6: 2,4 | E6: 8+
A7: OOP & C++ | B7: Polymorphism: Overloading (compile-time) vs Overriding (runtime) | C7: 5 | E7: 8+
A8: OOP & C++ | B8: Constructors: Default/Parameterized/Copy; Destructor | C8: 6 | E8: 6+
A9: OOP & C++ | B9: struct (default public) vs class (default private) | C9: 13 | E9: 3+
A10: OOP & C++ | B10: delete NULL = safe; delete vs delete[]; new vs malloc | C10: 9 | E10: 4+
A11: OOP & C++ | B11: File modes: ios::trunc/in/out/app/binary; Ctrl+F9 | C11: 11 | E11: 4+
A12: OOP & C++ | B12: Inline functions = SMALL & SIMPLE (not large/complex) | C12: 12 | E12: 3+
A13: DSA | B13: Stack: LIFO, Applications (String rev, Backtrack, Eval, Recursion) | C13: 16 | E13: 10+
A14: DSA | B14: Stack: NOT application = Async data transfer (that's Queue) | C14: 16 | E14: 3+
... A61: TOC/Web | B61: HTML=defines STRUCTURE; Server-side=PHP/Python/Node.js | C61: 85 | E61: 2+

Sheet 📝 Mock Test Log
A1: MOCK TEST LOG — Track All 12 Mock Tests | Target: 130+/150
A2: Mock Test # | B2: Day | C2: Date | D2: Language (/30) | E2: GS (/40) | F2: CS (/80) | G2: TOTAL (/150) | H2: % Score | I2: Rank Estimate | J2: Weak Topics Identified | K2: Action Plan for Next Test
A3: Mock Test 1 | B3: 60 | G3: =IF(D3+E3+F3=0,"",D3+E3+F3) | H3: =IF(G3="","",G3/150*100) | I3: =IF(G3="","",IF(G3>=140,"Top 10 Rank",IF(G3>=130,"Top 50 Rank",IF(G3>=120,"Top 100 Rank","Need Improvement"))))
A4: Mock Test 2 | B4: 92 | G4: =IF(D4+E4+F4=0,"",D4+E4+F4) | H4: =IF(G4="","",G4/150*100) | I4: =IF(G4="","",IF(G4>=140,"Top 10 Rank",IF(G4>=130,"Top 50 Rank",IF(G4>=120,"Top 100 Rank","Need Improvement"))))
A5: Mock Test 3 | B5: 107 | G5: =IF(D5+E5+F5=0,"",D5+E5+F5) | H5: =IF(G5="","",G5/150*100) | I5: =IF(G5="","",IF(G5>=140,"Top 10 Rank",IF(G5>=130,"Top 50 Rank",IF(G5>=120,"Top 100 Rank","Need Improvement"))))
A6: Mock Test 4 | B6: 111 | G6: =IF(D6+E6+F6=0,"",D6+E6+F6) | H6: =IF(G6="","",G6/150*100) | I6: =IF(G6="","",IF(G6>=140,"Top 10 Rank",IF(G6>=130,"Top 50 Rank",IF(G6>=120,"Top 100 Rank","Need Improvement"))))
A7: Mock Test 5 | B7: 113 | G7: =IF(D7+E7+F7=0,"",D7+E7+F7) | H7: =IF(G7="","",G7/150*100) | I7: =IF(G7="","",IF(G7>=140,"Top 10 Rank",IF(G7>=130,"Top 50 Rank",IF(G7>=120,"Top 100 Rank","Need Improvement"))))
A8: Mock Test 6 | B8: 115 | G8: =IF(D8+E8+F8=0,"",D8+E8+F8) | H8: =IF(G8="","",G8/150*100) | I8: =IF(G8="","",IF(G8>=140,"Top 10 Rank",IF(G8>=130,"Top 50 Rank",IF(G8>=120,"Top 100 Rank","Need Improvement"))))
A9: Mock Test 7 | B9: 123 | G9: =IF(D9+E9+F9=0,"",D9+E9+F9) | H9: =IF(G9="","",G9/150*100) | I9: =IF(G9="","",IF(G9>=140,"Top 10 Rank",IF(G9>=130,"Top 50 Rank",IF(G9>=120,"Top 100 Rank","Need Improvement"))))
A10: Mock Test 8 | B10: 127 | G10: =IF(D10+E10+F10=0,"",D10+E10+F10) | H10: =IF(G10="","",G10/150*100) | I10: =IF(G10="","",IF(G10>=140,"Top 10 Rank",IF(G10>=130,"Top 50 Rank",IF(G10>=120,"Top 100 Rank","Need Improvement"))))
A11: Mock Test 9 | B11: 130 | G11: =IF(D11+E11+F11=0,"",D11+E11+F11) | H11: =IF(G11="","",G11/150*100) | I11: =IF(G11="","",IF(G11>=140,"Top 10 Rank",IF(G11>=130,"Top 50 Rank",IF(G11>=120,"Top 100 Rank","Need Improvement"))))
A12: Mock Test 10 | B12: 137 | G12: =IF(D12+E12+F12=0,"",D12+E12+F12) | H12: =IF(G12="","",G12/150*100) | I12: =IF(G12="","",IF(G12>=140,"Top 10 Rank",IF(G12>=130,"Top 50 Rank",IF(G12>=120,"Top 100 Rank","Need Improvement"))))
A13: Mock Test 11 | B13: 142 | G13: =IF(D13+E13+F13=0,"",D13+E13+F13) | H13: =IF(G13="","",G13/150*100) | I13: =IF(G13="","",IF(G13>=140,"Top 10 Rank",IF(G13>=130,"Top 50 Rank",IF(G13>=120,"Top 100 Rank","Need Improvement"))))
A14: Mock Test 12 | B14: 147 | G14: =IF(D14+E14+F14=0,"",D14+E14+F14) | H14: =IF(G14="","",G14/150*100) | I14: =IF(G14="","",IF(G14>=140,"Top 10 Rank",IF(G14>=130,"Top 50 Rank",IF(G14>=120,"Top 100 Rank","Need Improvement"))))
A17: 📈 SCORE PROGRESSION
A18: Mock Test | B18: Total Score | C18: Target Line (130)
A19: Mock Test 1 | B19: =G3 | C19: 130
A20: Mock Test 2 | B20: =G4 | C20: 130
A21: Mock Test 3 | B21: =G5 | C21: 130
A22: Mock Test 4 | B22: =G6 | C22: 130
A23: Mock Test 5 | B23: =G7 | C23: 130
A24: Mock Test 6 | B24: =G8 | C24: 130
A25: Mock Test 7 | B25: =G9 | C25: 130
A26: Mock Test 8 | B26: =G10 | C26: 130
A27: Mock Test 9 | B27: =G11 | C27: 130
A28: Mock Test 10 | B28: =G12 | C28: 130
A29: Mock Test 11 | B29: =G13 | C29: 130
A30: Mock Test 12 | B30: =G14 | C30: 130

Sheet 📐 Formula Sheet
A1: ⚡ QUICK FORMULA SHEET — Memorize Before Exam
A2: Category | B2: Formula / Fact | C2: Example | D2: Memorized? (✅)
A3: CS — Paging | B3: Page offset bits = log₂(page size in bytes) | C3: 4KB = 2¹² → 12 bits
A4: CS — Paging | B4: Number of pages = Virtual address space / Page size | C4: 1MB space, 4KB page → 256 pages
A5: CS — MUX | B5: Select lines for MUX = log₂(number of inputs) | C5: 8:1 MUX → log₂(8) = 3 select lines
A6: CS — Digital | B6: Truth table rows = 2ⁿ (n = number of inputs) | C6: 4-input OR gate → 2⁴ = 16 rows
A7: CS — BST | B7: Catalan number C(n) = (2n)! / ((n+1)! × n!) | C7: C(4) = 14 distinct BSTs from 4 keys
A8: CS — Disk | B8: FCFS Total = Σ|position(i) – position(i-1)| | C8: Head 53 → 98: |53–98| = 45
A9: CS — Network | B9: IPv4 = 32 bits; IPv6 = 128 bits | C9: 192.168.1.1 = IPv4; 2001:db8::1 = IPv6
A10: CS — Complexity | B10: Binary search = O(log N) | C10: 1,000 elements → max ~10 comparisons
A11: CS — Complexity | B11: Merge sort = O(N log N) [always] | C11: N=1000 → ~10,000 operations
A12: CS — Complexity | B12: Bubble sort = O(N²) worst; O(N) best | C12: N=100 → worst 10,000; best 99
A13: CS — Complexity | B13: Infix to Postfix = O(N) | C13: Expression A+B*C: N=5 tokens → O(5)
A14: CS — Number Sys. | B14: Decimal 1234 → Binary = 10011010010 | C14: 1234 ÷ 2 repeatedly
... A27: GS — SQL | B27: ROUND(number, -1) rounds to nearest 10 | C27: ROUND(65.726,-1)=70; ROUND(54,-1)=50
